fuzzy_clustering/__init__.py
fuzzy_clustering/core/__init__.py
fuzzy_clustering/core/fuzzy.py
fuzzy_clustering/utils/__init__.py
fuzzy_clustering/utils/utils.py
Fuzzy_Clustering-1.0.0.dist-info/LICENSE
Fuzzy_Clustering-1.0.0.dist-info/METADATA
Fuzzy_Clustering-1.0.0.dist-info/WHEEL
Fuzzy_Clustering-1.0.0.dist-info/top_level.txt
Fuzzy_Clustering-1.0.0.dist-info/RECORD
