Metadata-Version: 2.1
Name: Fuzzy-Clustering
Version: 1.0.0
Summary: an implementation of fuzzy clustering algorithms
Home-page: https://github.com/Sam-damn/Fuzzy-Clustering
Author: Sameh Haidar
Author-email: samxxhaider@gmail.com
License: MIT
Keywords: fuzzy,cluster,fuzzy c means
Platform: UNKNOWN
Classifier: Programming Language :: Python :: 3
Classifier: License :: OSI Approved :: MIT License
Classifier: Operating System :: OS Independent
Requires-Python: >=3.6
License-File: LICENSE
Requires-Dist: numpy (>=1.16.4)
Provides-Extra: examples
Requires-Dist: matplotlib ; extra == 'examples'
Requires-Dist: opencv-python ; extra == 'examples'
Requires-Dist: scikit-image ; extra == 'examples'
Requires-Dist: scikit-learn ; extra == 'examples'
